<?xml version="1.0" encoding="UTF-8"?><!DOCTYPE task PUBLIC "-//OASIS//DTD DITA 1.3  Task//EN" "task.dtd">
<task id="ta_200-017" xml:lang="en-GB" translate="yes"><!--Audit sequence: 200-017 ;  Sequence: 017 ; Level: 3-->
   <title>View team members activity, boards, and cards</title>
   <shortdesc>-</shortdesc>
   <prolog>
      <source>https://trello.com/business-class</source>
      <metadata>
         <prodinfo>
            <prodname/>
         </prodinfo>
      </metadata>
   </prolog>
   <taskbody/>
</task>
